wfdanielpackagetest
