Metadata-Version: 2.1
Name: wfdanielpackagetest
Version: 0.2.5
Summary: Python package for my wfdanielpackagetest.
Home-page: https://github.com/danielmen-mx/wfdanielpackagetest
Download-URL: https://github.com/danielmen-mx/wfdanielpackagetest/archive/0.2.5.tar.gz
Author: D.Mendez
Author-email: pablomen1131@gmail.com
Classifier: Programming Language :: Python :: 3
Classifier: License :: OSI Approved :: MIT License
Classifier: Operating System :: OS Independent
Requires-Python: >=3
License-File: LICENSE
